pytotp_client/__init__.py
pytotp_client/__main__.py
pytotp_client/_cli.py
pytotp_client/_client.py
pytotp_client/_clipboard.py
pytotp_client/_colorizer.py
pytotp_client/_constants.py
pytotp_client-0.6.2.dist-info/LICENSE
pytotp_client-0.6.2.dist-info/METADATA
pytotp_client-0.6.2.dist-info/WHEEL
pytotp_client-0.6.2.dist-info/entry_points.txt
pytotp_client-0.6.2.dist-info/RECORD
