Metadata-Version: 2.3
Name: pytotp_client
Version: 0.6.2
Summary: TOTP client for macOS
License: MIT
Author: Elisei
Author-email: elisey.rav@gmail.com
Requires-Python: >=3.13,<4.0
Classifier: Operating System :: MacOS
Classifier: License :: OSI Approved :: MIT License
Classifier: Programming Language :: Python :: 3
Requires-Dist: pykeychain (>=2.0.1,<3.0.0)
Requires-Dist: pyotp (>=2.9.0,<3.0.0)
Requires-Dist: qrcode[pil] (>=8.2,<9.0)
Project-URL: Repository, https://github.com/elisey/pytotp_client
